c2p/__init__.py
c2p/__main__.py
c2p/cli.py
c2p/commands/__init__.py
c2p/commands/version.py
c2p/commands/tools/__init__.py
c2p/commands/tools/csv2oscal_cd.py
c2p/commands/tools/tools.py
c2p/commands/tools/viewer.py
c2p/common/__init__.py
c2p/common/c2p_base_model.py
c2p/common/err.py
c2p/common/logging.py
c2p/common/oscal.py
c2p/common/utils.py
c2p/framework/__init__.py
c2p/framework/c2p.py
c2p/framework/oscal_utils.py
c2p/framework/plugin_spec.py
c2p/framework/models/__init__.py
c2p/framework/models/c2p_config.py
c2p/framework/models/policy.py
c2p/framework/models/pvp_result.py
c2p/framework/models/raw_result.py
c2p/tools/__init__.py
c2p/tools/oscal_csv_to_json.py
c2p/tools/viewer/__init__.py
c2p/tools/viewer/template.py
c2p/tools/viewer/viewer.py
compliance_to_policy-0.5.0.dist-info/LICENSE
compliance_to_policy-0.5.0.dist-info/METADATA
compliance_to_policy-0.5.0.dist-info/WHEEL
compliance_to_policy-0.5.0.dist-info/entry_points.txt
compliance_to_policy-0.5.0.dist-info/top_level.txt
compliance_to_policy-0.5.0.dist-info/RECORD
