Metadata-Version: 2.1
Name: compliance-to-policy
Version: 0.5.0
Summary: Tools to bridge Compliance and Policy
Author-email: Takumi Yanagawa <yana1205dev@gmail.com>
License: Apache License
Project-URL: Homepage, https://github.com/oscal-compass/compliance-to-policy
Project-URL: Issues, https://github.com/oscal-compass/compliance-to-policy/issues
Classifier: Development Status :: 3 - Alpha
Classifier: Intended Audience :: Developers
Classifier: Programming Language :: Python :: 3
Classifier: Programming Language :: Python :: 3.9
Classifier: License :: OSI Approved :: Apache Software License
Classifier: Operating System :: OS Independent
Requires-Python: >=3.9
License-File: LICENSE
Requires-Dist: compliance-trestle ~=3.3
Requires-Dist: PyGithub ==1.58.0
Requires-Dist: jq ==1.6.0
Requires-Dist: pluggy
Provides-Extra: dev
Requires-Dist: build >=1.0.3 ; extra == 'dev'
Requires-Dist: pyclean ; extra == 'dev'
Requires-Dist: pytest >=8.0.0 ; extra == 'dev'
Requires-Dist: pre-commit >=2.4.0 ; extra == 'dev'
Requires-Dist: pep8-naming ; extra == 'dev'
Requires-Dist: toml-cli ; extra == 'dev'
Requires-Dist: types-PyYAML ; extra == 'dev'
Requires-Dist: types-setuptools ; extra == 'dev'
Requires-Dist: mkdocs ; extra == 'dev'
Requires-Dist: mkdocs-redirects ; extra == 'dev'
Requires-Dist: mkdocstrings-python ; extra == 'dev'
Requires-Dist: black ; extra == 'dev'
Requires-Dist: isort ; extra == 'dev'
Requires-Dist: pylint ; extra == 'dev'
